MANIFEST.in
README.md
setup.cfg
setup.py
pycocotb/__init__.py
pycocotb/constants.py
pycocotb/hdlSimulator.py
pycocotb/process_utils.py
pycocotb/simCalendar.py
pycocotb/triggers.py
pycocotb/utils.py
pycocotb.egg-info/PKG-INFO
pycocotb.egg-info/SOURCES.txt
pycocotb.egg-info/dependency_links.txt
pycocotb.egg-info/not-zip-safe
pycocotb.egg-info/requires.txt
pycocotb.egg-info/top_level.txt
pycocotb/agents/__init__.py
pycocotb/agents/base.py
pycocotb/agents/clk.py
pycocotb/agents/handshaked.py
pycocotb/agents/rst.py
pycocotb/agents/peripheral/__init__.py
pycocotb/agents/peripheral/i2c.py
pycocotb/agents/peripheral/tristate.py
pycocotb/agents/peripheral/uart.py
pycocotb/basic_hdl_simulator/__init__.py
pycocotb/basic_hdl_simulator/io.py
pycocotb/basic_hdl_simulator/model.py
pycocotb/basic_hdl_simulator/model_utils.py
pycocotb/basic_hdl_simulator/proxy.py
pycocotb/basic_hdl_simulator/rtlSimulator.py
pycocotb/basic_hdl_simulator/sim_utils.py
pycocotb/tests/__init__.py
pycocotb/tests/all.py
pycocotb/tests/common.py
pycocotb/tests/example_agents.py
pycocotb/tests/i2c_test.py
pycocotb/tests/verilatorCntr_test.py
pycocotb/tests/verilatorHandshakedWire_test.py
pycocotb/tests/verilatorHierarchy_test.py
pycocotb/tests/wire_test.py
pycocotb/verilator/__init__.py
pycocotb/verilator/fs_utils.py
pycocotb/verilator/simulator_gen.py
pycocotb/verilator/c_files/pycocotb_common.h
pycocotb/verilator/c_files/pycocotb_sim.cpp
pycocotb/verilator/c_files/pycocotb_sim.h
pycocotb/verilator/c_files/signal_array_mem_proxy.cpp
pycocotb/verilator/c_files/signal_array_mem_proxy.h
pycocotb/verilator/c_files/signal_mem_proxy.cpp
pycocotb/verilator/c_files/signal_mem_proxy.h
pycocotb/verilator/c_files/sim_io.cpp
pycocotb/verilator/c_files/sim_io.h
pycocotb/verilator/templates/__init__.py
pycocotb/verilator/templates/verilator_sim.cpp.template